[
  {
    "id": 1,
    "personId": 3,
    "type": "Financial",
    "notes": null,
    "isActive": true,
    "amount": 5000
  },
  {
    "id": 2,
    "personId": 17,
    "type": "Financial",
    "notes": null,
    "isActive": true,
    "amount": 40000
  },
  {
    "id": 3,
    "personId": 18,
    "type": "Financial",
    "notes": null,
    "isActive": true,
    "amount": 50000
  },
  {
    "id": 4,
    "personId": 33,
    "type": "Financial",
    "notes": null,
    "isActive": true,
    "amount": 5000
  },
  {
    "id": 5,
    "personId": 42,
    "type": "Other",
    "notes": null,
    "isActive": true
  },
  {
    "id": 6,
    "personId": 65,
    "type": "Financial",
    "notes": null,
    "isActive": true,
    "amount": 40000
  },
  {
    "id": 7,
    "personId": 70,
    "type": "Financial",
    "notes": null,
    "isActive": true,
    "amount": 15000
  },
  {
    "id": 8,
    "personId": 71,
    "type": "Financial",
    "notes": null,
    "isActive": true,
    "amount": 30000
  },
  {
    "id": 9,
    "personId": 74,
    "type": "Other",
    "notes": null,
    "isActive": true
  },
  {
    "id": 10,
    "personId": 77,
    "type": "Financial",
    "notes": null,
    "isActive": true,
    "amount": 15000
  },
  {
    "id": 11,
    "personId": 80,
    "type": "Financial",
    "notes": null,
    "isActive": true,
    "amount": 5000
  },
  {
    "id": 12,
    "personId": 81,
    "type": "Financial",
    "notes": null,
    "isActive": true,
    "amount": 10000
  },
  {
    "id": 13,
    "personId": 92,
    "type": "Financial",
    "notes": null,
    "isActive": true,
    "amount": 20000
  },
  {
    "id": 14,
    "personId": 107,
    "type": "Financial",
    "notes": null,
    "isActive": true,
    "amount": 15000
  },
  {
    "id": 15,
    "personId": 109,
    "type": "Other",
    "notes": null,
    "isActive": true
  },
  {
    "id": 16,
    "personId": 130,
    "type": "Other",
    "notes": null,
    "isActive": true
  },
  {
    "id": 17,
    "personId": 152,
    "type": "Financial",
    "notes": null,
    "isActive": true,
    "amount": 15000
  },
  {
    "id": 18,
    "personId": 155,
    "type": "Financial",
    "notes": null,
    "isActive": true,
    "amount": 20000
  },
  {
    "id": 19,
    "personId": 156,
    "type": "Financial",
    "notes": null,
    "isActive": true,
    "amount": 25000
  },
  {
    "id": 20,
    "personId": 191,
    "type": "Financial",
    "notes": null,
    "isActive": true,
    "amount": 15000
  },
  {
    "id": 21,
    "personId": 192,
    "type": "Financial",
    "notes": null,
    "isActive": true,
    "amount": 15000
  },
  {
    "id": 22,
    "personId": 194,
    "type": "Financial",
    "notes": null,
    "isActive": true,
    "amount": 10000
  },
  {
    "id": 23,
    "personId": 196,
    "type": "Financial",
    "notes": null,
    "isActive": true,
    "amount": 10000
  },
  {
    "id": 24,
    "personId": 197,
    "type": "Other",
    "notes": null,
    "isActive": true
  },
  {
    "id": 25,
    "personId": 206,
    "type": "Financial",
    "notes": null,
    "isActive": true,
    "amount": 30000
  },
  {
    "id": 26,
    "personId": 207,
    "type": "Financial",
    "notes": null,
    "isActive": true,
    "amount": 10000
  },
  {
    "id": 27,
    "personId": 212,
    "type": "Financial",
    "notes": null,
    "isActive": true,
    "amount": 5000
  },
  {
    "id": 28,
    "personId": 220,
    "type": "Other",
    "notes": null,
    "isActive": true
  },
  {
    "id": 29,
    "personId": 221,
    "type": "Financial",
    "notes": null,
    "isActive": true,
    "amount": 50000
  },
  {
    "id": 30,
    "personId": 224,
    "type": "Financial",
    "notes": null,
    "isActive": true,
    "amount": 20000
  },
  {
    "id": 31,
    "personId": 233,
    "type": "Financial",
    "notes": null,
    "isActive": true,
    "amount": 10000
  }
]